aioN26/__init__.py
aioN26/api.py
aioN26-0.0.6.dist-info/LICENSE
aioN26-0.0.6.dist-info/METADATA
aioN26-0.0.6.dist-info/WHEEL
aioN26-0.0.6.dist-info/top_level.txt
aioN26-0.0.6.dist-info/RECORD
