Metadata-Version: 2.1
Name: aioN26
Version: 0.0.6
Summary: Unofficial asynchronous API interface to the N26 bank
Home-page: https://www.cygnuskraft.es/contact-us/
Author: Marcelo Troitino
Author-email: marcelo@cygnuskraft.es
License: MIT
Keywords: N26 asyncio aioN26 API
Platform: UNKNOWN
Classifier: Development Status :: 4 - Beta
Classifier: Framework :: AsyncIO
Classifier: Intended Audience :: Developers
Classifier: Operating System :: OS Independent
Classifier: Programming Language :: Python :: 3.10
Classifier: Topic :: Utilities
Classifier: License :: OSI Approved :: MIT License
Requires-Python: >=3.10
License-File: LICENSE
Requires-Dist: aiohttp (==3.8.1)
Requires-Dist: certifi (==2021.10.8)
Requires-Dist: click (==8.0.3)
Requires-Dist: pycryptodome (==3.11.0)
Requires-Dist: python-dotenv (==0.19.2)
Requires-Dist: aiofiles (==0.7.0)
